{
	"animations": [
		{
			"offsets": [
				0,
				0
			],
			"loop": false,
			"fps": 24,
			"anim": "singDOWN",
			"indices": [],
			"name": "BF NOTE DOWN"
		},
		{
			"offsets": [
				1,
				10
			],
			"loop": false,
			"fps": 24,
			"anim": "singLEFT",
			"indices": [],
			"name": "BF NOTE LEFT"
		},
		{
			"offsets": [
				-16,
				7
			],
			"loop": false,
			"fps": 24,
			"anim": "singRIGHT",
			"indices": [],
			"name": "BF NOTE RIGHT"
		},
		{
			"offsets": [
				7,
				19
			],
			"loop": false,
			"fps": 24,
			"anim": "singUP",
			"indices": [],
			"name": "BF NOTE UP"
		},
		{
			"offsets": [
				0,
				0
			],
			"loop": true,
			"fps": 24,
			"anim": "idle",
			"indices": [],
			"name": "BF IDLE"
		}
	],
	"no_antialiasing": false,
	"image": "characters/HD_BF_SONIC",
	"position": [
		0,
		350
	],
	"healthicon": "bfhd",
	"flip_x": true,
	"healthbar_colors": [
		49,
		176,
		209
	],
	"camera_position": [
		260,
		50
	],
	"sing_duration": 4,
	"scale": 1
}